setup.py
glancespeed/__init__.py
glancespeed/core.py
glancespeed/main.py
glancespeed.egg-info/PKG-INFO
glancespeed.egg-info/SOURCES.txt
glancespeed.egg-info/dependency_links.txt
glancespeed.egg-info/entry_points.txt
glancespeed.egg-info/not-zip-safe
glancespeed.egg-info/requires.txt
glancespeed.egg-info/top_level.txt