Metadata-Version: 1.0
Name: glancespeed
Version: 0.0.2
Summary: Nephila's internal tool to show Google PageSpeed Insights reports differences
Home-page: UNKNOWN
Author: Andrea Stagi
Author-email: stagi.andrea@gmail.com
License: MIT
Keywords: measure optimize website page size pagespeed insights reporting psi
Platform: UNKNOWN
